Metadata-Version: 2.1
Name: nesterlnvn
Version: 1.0.0
Summary: Im testing a module
Home-page: UNKNOWN
Author: Long Nguyen
Author-email: test@gmail.com
License: UNKNOWN
Platform: UNKNOWN
